<?xml version="1.0" encoding="UTF-8" standalone="yes"?>
<trains>
    <train id="10">
        <from>Lviv</from>
        <to>Tcherkasy</to>
        <date>19.01.2013</date>
    </train>
    <train id="3">
        <from>Kyiv</from>
        <to>Kharkiv</to>
        <date>19.01.2013</date>
    </train>
    <train id="9">
        <from>Kyiv</from>
        <to>Mykolayv</to>
        <date>19.01.2013</date>
    </train>
    <train id="7">
        <from>Kyiv</from>
        <to>Uzhgorod</to>
        <date>19.01.2013</date>
    </train>
    <train id="13">
        <from>Kyiv</from>
        <to>Ternopil</to>
        <date>19.01.2013</date>
        <departure>00:00</departure>
    </train>
    <train id="12">
        <from>Lviv</from>
        <to>Tcherkasy</to>
        <date>22.01.2013</date>
    </train>
    <train id="5">
        <from>Kyiv</from>
        <to>Dnipro</to>
        <date>19.01.2013</date>
    </train>
    <train id="1">
        <from>Kyiv</from>
        <to>Donetsk</to>
        <date>19.01.2013</date>
    </train>
    <train id="8">
        <from>Lviv</from>
        <to>Odessa</to>
        <date>19.01.2013</date>
    </train>
    <train id="11">
        <from>Lviv</from>
        <to>Tcherkasy</to>
        <date>19.01.2013</date>
    </train>
    <train id="4">
        <from>Lviv</from>
        <to>Vinnytsya</to>
        <date>19.01.2013</date>
    </train>
    <train id="13">
        <from>Kyiv</from>
        <to>Ternopil</to>
        <date>19.01.2013</date>
        <departure>15:35</departure>
    </train>
    <train id="13">
        <from>Kyiv</from>
        <to>Ternopil</to>
        <date>19.01.2013</date>
        <departure>00:00</departure>
    </train>
    <train id="2">
        <from>Lviv</from>
        <to>Donetsk</to>
        <date>19.01.2013</date>
    </train>
    <train id="6">
        <from>Lviv</from>
        <to>Melitopol</to>
        <date>21.01.2013</date>
    </train>
</trains>
